{
  "score": 79,
  "rawScore": 58,
  "signal": "positive",
  "key_themes": [
    "Frequent analyst upgrades and raised price targets ($206–$220)",
    "Leverage to geopolitical oil price strength and energy security",
    "Long-term project expansions, discoveries, and cost-cutting targets",
    "Reliable dividend growth and shareholder returns",
    "Near-term Q1 headwinds (timing effects, legal charges) amid volatility"
  ],
  "summary": "Chevron (CVX) maintains solidly positive sentiment among analysts and longer-term investors despite a recent pullback from March highs above $210 to around $184 as of mid-April 2026. Multiple Wall Street upgrades, higher oil price leverage from geopolitical tensions, new discoveries, Venezuela-related moves, and a Supreme Court win support optimism, with many price targets now above $210 and potential for $250–300 over several years. Q1 2026 faces notable one-time headwinds (negative timing effects of $2.7–3.7B, working capital outflows, legal charges), but these are viewed as transitory against strong upstream commodity tailwinds, ongoing cost discipline ($3–4B structural cuts targeted), and consistent capital returns.",
  "sources": "15+ recent news articles and analyst notes (Yahoo Finance, TipRanks, CNBC, RBC, JPM, BofA, Goldman Sachs), 15+ X posts (mix of bullish longer-term calls and recent promotional/spam noise), Investor forums (StockTwits, Yahoo Finance, Investing.com) and SEC filings"
}