{
  "score": 83,
  "rawScore": 65,
  "signal": "positive",
  "key_themes": [
    "Record revenue growth, strong backlog expansion, and improving cash flow",
    "Major defense/national security contracts and government demand",
    "AI innovation, satellite deployments, and tech advancements",
    "Space economy momentum and SpaceX IPO tailwinds",
    "Valuation concerns, high multiples, and recent insider sales after massive rally"
  ],
  "summary": "Planet Labs (PL) is enjoying strongly positive sentiment after delivering record FY2026 revenue of $308 million (+26% YoY), Q4 revenue of $86.8 million (+41%), and a backlog exceeding $900 million (+79%), backed by multiple nine-figure defense contracts with Sweden, Japan, and Germany.[[1]](https://finance.yahoo.com/markets/stocks/articles/planet-labs-pbc-pl-q4-030057819.html)[[2]](https://investors.planet.com/financials/quarterly-results/default.aspx) The stock has surged nearly 10x in the past year, repeatedly hitting new highs amid AI satellite deployments (including NVIDIA-powered object detection) and broader space-sector hype tied to rumored SpaceX IPO activity, with investors widely sharing 700%+ gains and calling for further upside on technical breakouts.[[3]](https://finance.yahoo.com/markets/stocks/articles/too-consider-planet-labs-pl-160643498.html)[[4]](https://www.fool.com/investing/2026/04/16/why-did-planet-labs-stock-pop-today/) While analyst consensus leans Buy, average price targets (~$29–$30) lag the current ~$38–39 price, several DCF models flag overvaluation, and recent insider sales (including by the CEO and directors in April) introduce some caution, momentum remains firmly bullish overall.[[5]](https://finance.yahoo.com/quote/PL/insider-transactions/)",
  "sources": "20+ news articles and analyst reports (Yahoo Finance, Motley Fool, TipRanks, MarketBeat, company filings), 15+ X posts and investor discussions (bullish trader calls, CEO updates, top performer lists)"
}