{
  "ticker": "YOU",
  "company": "YouGov Plc",
  "slug": "yougovplc",
  "date": "2026-04-19",
  "queries": [
    {
      "query": "YOU YouGov Plc earnings Q1 2026",
      "hits": [
        {
          "title": "Earnings call transcript: YouGov Q1 2026 shows resilient growth amid sector challenges By Investing.com",
          "url": "https://www.investing.com/news/transcripts/earnings-call-transcript-yougov-q1-2026-shows-resilient-growth-amid-sector-challenges-93CH-4598879",
          "snippet": "The company’s earnings per share (EPS) stood at <strong>11.4 pence</strong>. Revenue reached GBP 194.8 million, reflecting YouGov’s strong market position amid a sector experiencing flat or negative g"
        },
        {
          "title": "YouGov (YOU) Earnings Date and Reports 2026 $YOU",
          "url": "https://www.marketbeat.com/stocks/LON/YOU/earnings/",
          "snippet": "When is YouGov&#x27;s next earnings announcement? View the latest YOU earnings date, analysts forecasts, earnings history, and conference call transcripts."
        },
        {
          "title": "With 74% ownership, YouGov plc (LON:YOU) boasts of strong institutional backing",
          "url": "https://finance.yahoo.com/news/74-ownership-yougov-plc-lon-072802878.html",
          "snippet": "AIM:YOU Earnings and Revenue Growth February 15th 2026 · Since institutional investors own more than half the issued stock, the board will likely have to pay attention to their preferences. Hedge fund"
        },
        {
          "title": "YouGov plc (YOU.L) Stock Price, News, Quote & History - Yahoo Finance",
          "url": "https://finance.yahoo.com/quote/YOU.L/",
          "snippet": "YouGov plc was incorporated in 1998 and is headquartered in London, the United Kingdom. www.yougov.com ... <strong>Trailing total returns as of 4/10/2026, which may include dividends or other distribu"
        },
        {
          "title": "YouGov Plc (YOU) Stock Price & News - Google Finance",
          "url": "https://www.google.com/finance/quote/YOU:LON",
          "snippet": "Get the latest YouGov Plc (YOU) real-time quote, historical performance, charts, and other financial information to help you make more informed trading and investment decisions."
        }
      ],
      "count": 5
    },
    {
      "query": "YOU YouGov Plc news April 2026",
      "hits": [
        {
          "title": "Iran, Trump's approval, inflation, taxes, spending, Bondi, and more: April 3 - 6, 2026 Economist/YouGov Poll",
          "url": "https://yougov.com/en-us/articles/54483-iran-donald-trump-approval-inflation-taxes-spending-pam-bondi-nato-april-3-6-2026-economist-yougov-poll",
          "snippet": "See the toplines and crosstabs for the April 3 - 6, 2026 Economist/YouGov Poll"
        },
        {
          "title": "YouGov plc (YOU.L) Stock Price, News, Quote & History - Yahoo Finance",
          "url": "https://finance.yahoo.com/quote/YOU.L/",
          "snippet": "YouGov plc was incorporated in 1998 and is headquartered in London, the United Kingdom. www.yougov.com ... <strong>Trailing total returns as of 4/10/2026, which may include dividends or other distribu"
        },
        {
          "title": "Voting intention, 6-7 April 2026: Ref 24%, Con 19%, Lab 16%, Grn 16%, LD 13%",
          "url": "https://yougov.com/en-gb/articles/54492-voting-intention-6-7-april-2026-ref-24-con-19-lab-16-grn-16-ld-13",
          "snippet": "2026 Danish general election: first YouGov LSS election model shows close race between left and right blocs"
        },
        {
          "title": "Voting intention, 12-13 April 2026: Ref 24%, Con 19%, Grn 18%, Lab 17%, LD 13%",
          "url": "https://yougov.com/en-gb/articles/54524-voting-intention-12-13-april-2026-ref-24-con-19-grn-18-lab-17-ld-13",
          "snippet": "2026 Danish general election: first YouGov LSS election model shows close race between left and right blocs"
        },
        {
          "title": "Iran, Trump's health, gas prices, and more: April 10 - 13, 2026 Economist/YouGov Poll",
          "url": "https://yougov.com/en-us/articles/54536-iran-gas-prices-donald-trump-health-jd-vance-marijuana-april-10-13-2026-economist-yougov-poll",
          "snippet": "... Americans&#x27; evaluations of gas ... Most Americans approve of the U.S. ceasefire with Iran ... <strong>Iran, Trump&#x27;s approval, inflation, taxes, spending, Bondi, and more</strong>: April 3"
        }
      ],
      "count": 5
    },
    {
      "query": "YOU YouGov Plc stock analysis",
      "hits": [
        {
          "title": "YouGov plc (YOU.L) Stock Price, News, Quote & History - Yahoo Finance",
          "url": "https://finance.yahoo.com/quote/YOU.L/",
          "snippet": "YouGov plc was incorporated in 1998 and is headquartered in London, the United Kingdom. www.yougov.com ... <strong>Trailing total returns as of 4/10/2026, which may include dividends or other distribu"
        },
        {
          "title": "YouGov (AIM:YOU) - Stock Analysis - Simply Wall St",
          "url": "https://simplywall.st/stocks/gb/media/aim-you/yougov-shares",
          "snippet": "See what 36 others think this stock is worth. Follow their fair value or set your own to get alerts. ... Key Takeaways YouGov&#x27;s platform expansion and automation are set to accelerate operating l"
        },
        {
          "title": "YouGov (YOU) Share Price, Stock Value, News & Analysis $YOU",
          "url": "https://www.marketbeat.com/stocks/LON/YOU/",
          "snippet": "Should You Buy or Sell YouGov Stock? Get The Latest YOU Stock Analysis, Price Target, Dividend Info, and Headlines at MarketBeat."
        },
        {
          "title": "YouGov plc (YUGVF) Stock Price, Quote, News & Analysis | Seeking Alpha",
          "url": "https://seekingalpha.com/symbol/YUGVF",
          "snippet": "A high-level overview of YouGov plc (YUGVF) stock. View (YUGVF) real-time stock price, chart, news, analysis, analyst reviews and more."
        },
        {
          "title": "YouGov: Even A Conservative Outlook Offers A Significant Margin Of Safety (OTCMKTS:YUGVF) | Seeking Alpha",
          "url": "https://seekingalpha.com/article/4866861-yougov-even-a-conservative-outlook-offers-a-significant-margin-of-safety",
          "snippet": "<strong>YouGov plc presents a deep value opportunity with nearly 300% upside in my neutral scenario, warranting a Strong Buy rating</strong>. Click for my YUGVF stock analysis."
        }
      ],
      "count": 5
    },
    {
      "query": "YOU YouGov Plc guidance 2026",
      "hits": [
        {
          "title": "With 74% ownership, YouGov plc (LON:YOU) boasts of strong institutional backing",
          "url": "https://finance.yahoo.com/news/74-ownership-yougov-plc-lon-072802878.html",
          "snippet": "AIM:YOU Earnings and Revenue Growth February 15th 2026 · Since institutional investors own more than half the issued stock, the board will likely have to pay attention to their preferences. Hedge fund"
        },
        {
          "title": "YouGov (AIM:YOU) - Stock Analysis - Simply Wall St",
          "url": "https://simplywall.st/stocks/gb/media/aim-you/yougov-shares",
          "snippet": "Key Takeaways <strong>YouGov&#x27;s platform expansion and automation are set to accelerate operating leverage, margin expansion, and recurring revenues beyond current analyst expectations</strong>."
        },
        {
          "title": "YouGov plc 2026 Q2 - Results - Earnings Call Presentation (OTCMKTS:YUGVF) 2026-03-25 | Seeking Alpha",
          "url": "https://seekingalpha.com/article/4885621-yougov-plc-2026-q2-results-earnings-call-presentation",
          "snippet": "2026-03-25. The following slide deck was published by YouGov plc in conjunction with their 2026 Q2 earnings call."
        },
        {
          "title": "Earnings call transcript: YouGov Q1 2026 shows resilient growth amid sector challenges By Investing.com",
          "url": "https://ng.investing.com/news/transcripts/earnings-call-transcript-yougov-q1-2026-shows-resilient-growth-amid-sector-challenges-93CH-2426806",
          "snippet": "Could I just remind anyone wanting ... much. The first one is, &quot;<strong>You are pursuing investment in FY 2026, but are expecting the Value Delivery Plan to deliver enhancements to profitability "
        },
        {
          "title": "YouGov Plc - YUGVF - Stock Price & News | The Motley Fool",
          "url": "https://www.fool.com/quote/otc/yugvf/",
          "snippet": "Q2 2026YOY CHG · Net Cash · $176.78M · +1.0% Accounts Receivable · $80.29M · +6.1% Inventory · $0.00 · N/A · Long Term Debt · $150.48M · -20.0% Short Term Debt · $59.09M · +35.2% Return on Assets · 2."
        }
      ],
      "count": 5
    }
  ],
  "summary": "[YOU YouGov Plc earnings Q1 2026](https://www.investing.com/news/transcripts/earnings-call-transcript-yougov-q1-2026-shows-resilient-growth-amid-sector-challenges-93CH-4598879) Earnings call transcript: YouGov Q1 2026 shows resilient growth amid sect\n[YOU YouGov Plc news April 2026](https://yougov.com/en-us/articles/54483-iran-donald-trump-approval-inflation-taxes-spending-pam-bondi-nato-april-3-6-2026-economist-yougov-poll) Iran, Trump's approval, inflation, taxes, spending, Bondi, and more: Apr\n[YOU YouGov Plc stock analysis](https://finance.yahoo.com/quote/YOU.L/) YouGov plc (YOU.L) Stock Price, News, Quote & History - Yahoo Finance — YouGov plc was incorporated in 1998 and is headquartered in London, the United Kingdom. www.yougov.com ...\n[YOU YouGov Plc guidance 2026](https://finance.yahoo.com/news/74-ownership-yougov-plc-lon-072802878.html) With 74% ownership, YouGov plc (LON:YOU) boasts of strong institutional backing — AIM:YOU Earnings and Revenue Growth February 15th 2026 · Since",
  "gatheredAt": "2026-04-19T16:17:07.548Z"
}