{
  "score": 42,
  "signal": "negative",
  "key_themes": [
    "exploration challenges",
    "market uncertainty",
    "limited catalysts",
    "price decline"
  ],
  "summary": "Panther Metals plc (PALM.L) shows a negative sentiment with recent news highlighting operational challenges in exploration projects and a lack of significant positive updates. Analyst tone remains cautious, and price momentum has been downward, with no major near-term catalysts to drive recovery.",
  "raw": "{\n  \"score\": -20,\n  \"signal\": \"negative\",\n  \"key_themes\": [\"exploration challenges\", \"market uncertainty\", \"limited catalysts\", \"price decline\"],\n  \"summary\": \"Panther Metals plc (PALM.L) shows a negative sentiment with recent news highlighting operational challenges in exploration projects and a lack of significant positive updates. Analyst tone remains cautious, and price momentum has been downward, with no major near-term catalysts to drive recovery.\"\n}"
}