{
  "meta": {
    "ticker": "SMR",
    "company": "SMR - NuScale Power Corporation",
    "exchange": null,
    "isin": "US67079K1007",
    "date": "2026-04-18",
    "datePublished": "2026-04-18",
    "recommendation": "BUY",
    "recommendationNote": "OPPORTUNISTIC BUY",
    "conviction": 69,
    "lastRefreshed": "2026-04-18T15:09:10.388Z",
    "universes": [
      "watchlist"
    ]
  },
  "price": {
    "current": 12.65,
    "currency": "USD",
    "marketCap": "4340333779",
    "pe": null,
    "eps": -2.17,
    "week52High": 57.42,
    "week52Low": 8.85,
    "beta": 2.27,
    "avgVolume": "24462171",
    "sharesOutstanding": null
  },
  "grok": {
    "score": 42,
    "signal": "negative",
    "keyThemes": [
      "regulatory challenges",
      "project delays",
      "cost concerns",
      "market competition",
      "investor skepticism"
    ],
    "summary": "NuScale Power Corporation (SMR) faces a negative sentiment due to recent news highlighting regulatory hurdles and project delays, compounded by analyst concerns over rising costs and competition in the small modular reactor space. Price momentum has been weak, with no significant near-term catalysts to drive positive sentiment.",
    "bullCase": "",
    "bearCase": "",
    "sources": ""
  },
  "scenario": {
    "bullProbability": 29,
    "bullScore": 88,
    "baseProbability": 54,
    "baseScore": 68,
    "bearProbability": 17,
    "bearScore": 38,
    "conviction": 69
  },
  "sections": {
    "executiveSummary": {
      "text": "NuScale is one of the most recognisable listed names in advanced nuclear because it carries a real regulatory credential, the first U.S. NRC-approved SMR design. That matters. It gives the company a level of technical and policy credibility many earlier-stage peers do not have."
    },
    "businessModel": {
      "text": ""
    },
    "financialSnapshot": {
      "price": 12.65,
      "pe": null,
      "eps": -2.17,
      "marketCap": "4340333779",
      "week52High": 57.42,
      "week52Low": 8.85,
      "revenueTTM": null,
      "grossMargin": null
    },
    "recentCatalysts": {
      "text": ""
    },
    "thesisEvaluation": {
      "text": ""
    },
    "keyRisks": {
      "text": ""
    },
    "whoShouldOwnIt": {
      "text": ""
    },
    "recommendation": {
      "text": ""
    },
    "entry": {
      "text": ""
    },
    "sources": {
      "text": ""
    }
  },
  "scores": {
    "current": {
      "score": 69,
      "band": "BUY",
      "date": "2026-04-18",
      "delta": "3",
      "reason": "Formula fix"
    },
    "history": [
      {
        "date": "2026-04-08",
        "conviction": 46
      },
      {
        "date": "2026-04-16",
        "conviction": 46
      }
    ]
  }
}