{
  "ticker": "DIS",
  "date": "2026-04-17",
  "score": 58,
  "signal": "positive",
  "key_themes": [
    "Cost restructuring and layoffs for operational efficiency",
    "Improving streaming margins and Disney+ profitability",
    "Record performance in theme parks and experiences",
    "Bullish analyst upgrades with average price target ~$128",
    "Insider buying, dividend increase, and undervaluation signals"
  ],
  "sources": [
    "20+ recent news articles (Yahoo Finance, CNBC, Seeking Alpha, TipRanks)",
    "15+ X posts from semantic and keyword searches (March-April 2026)",
    "Multiple Reddit threads (r/ValueInvesting, r/stocks, r/dividends)"
  ],
  "summary": "As of mid-April 2026, Disney (DIS) trades near $106 with a constructive investor sentiment driven by aggressive cost-cutting, including up to 1,000 layoffs under new CEO Josh D’Amaro, particularly impacting Marvel but aimed at boosting margins and efficiency. Streaming (Disney+/Hulu) continues to improve profitability (SVOD operating income up sharply in Q1), parks/experiences hit records, and analysts remain bullish with an average price target around $128 and recent upgrades despite a mixed Q1 earnings reaction earlier this year. X posts and Reddit discussions highlight insider director purchases, a dividend hike, long-term business expansion since 2015 despite flat stock performance, and optimism for a 2026 turnaround.",
  "fetchedAt": "2026-04-17T17:06:54.283Z"
}