{
  "ticker": "CRS",
  "company": "Carpenter Technology Corp",
  "slug": "carpentertechnologycorp",
  "date": "2026-04-20",
  "queries": [
    {
      "query": "CRS Carpenter Technology Corp earnings Q1 2026",
      "error": "HTTP 402",
      "hits": []
    },
    {
      "query": "CRS Carpenter Technology Corp news April 2026",
      "error": "HTTP 402",
      "hits": []
    },
    {
      "query": "CRS Carpenter Technology Corp stock analysis",
      "error": "HTTP 402",
      "hits": []
    },
    {
      "query": "CRS Carpenter Technology Corp guidance 2026",
      "error": "HTTP 402",
      "hits": []
    }
  ],
  "summary": "",
  "gatheredAt": "2026-04-20T17:04:23.076Z"
}